odoo10_addon_partner_stock_risk-10.0.1.0.0-py2.7-nspkg.pth
odoo/addons/partner_stock_risk/README.rst
odoo/addons/partner_stock_risk/__init__.py
odoo/addons/partner_stock_risk/__manifest__.py
odoo/addons/partner_stock_risk/i18n/ca.po
odoo/addons/partner_stock_risk/i18n/de.po
odoo/addons/partner_stock_risk/i18n/es.po
odoo/addons/partner_stock_risk/i18n/es_AR.po
odoo/addons/partner_stock_risk/i18n/es_MX.po
odoo/addons/partner_stock_risk/i18n/fi.po
odoo/addons/partner_stock_risk/i18n/fr.po
odoo/addons/partner_stock_risk/i18n/gl.po
odoo/addons/partner_stock_risk/i18n/hr.po
odoo/addons/partner_stock_risk/i18n/it.po
odoo/addons/partner_stock_risk/i18n/pt.po
odoo/addons/partner_stock_risk/i18n/pt_BR.po
odoo/addons/partner_stock_risk/i18n/ro.po
odoo/addons/partner_stock_risk/i18n/sl.po
odoo/addons/partner_stock_risk/i18n/tr.po
odoo/addons/partner_stock_risk/i18n/tr_TR.po
odoo/addons/partner_stock_risk/i18n/vi_VN.po
odoo/addons/partner_stock_risk/i18n/zh_CN.po
odoo/addons/partner_stock_risk/models/__init__.py
odoo/addons/partner_stock_risk/models/stock.py
odoo/addons/partner_stock_risk/tests/__init__.py
odoo/addons/partner_stock_risk/tests/test_partner_stock_risk.py
odoo10_addon_partner_stock_risk-10.0.1.0.0.dist-info/DESCRIPTION.rst
odoo10_addon_partner_stock_risk-10.0.1.0.0.dist-info/METADATA
odoo10_addon_partner_stock_risk-10.0.1.0.0.dist-info/RECORD
odoo10_addon_partner_stock_risk-10.0.1.0.0.dist-info/WHEEL
odoo10_addon_partner_stock_risk-10.0.1.0.0.dist-info/metadata.json
odoo10_addon_partner_stock_risk-10.0.1.0.0.dist-info/namespace_packages.txt
odoo10_addon_partner_stock_risk-10.0.1.0.0.dist-info/top_level.txt
